setup.py
dj_userlog.egg-info/PKG-INFO
dj_userlog.egg-info/SOURCES.txt
dj_userlog.egg-info/dependency_links.txt
dj_userlog.egg-info/requires.txt
dj_userlog.egg-info/top_level.txt
userlog/__init__.py
userlog/models.py
userlog/serilalizers.py
userlog/signals.py
userlog/views.py