Metadata-Version: 2.1
Name: dj-userlog
Version: 0.1
Requires-Dist: Django
Requires-Dist: djangorestframework
Requires-Dist: django-filter
